Dominate_Layui/Core.py
Dominate_Layui/__init__ .py
Dominate_Layui/__pycache__/Core.cpython-36.pyc
Dominate_Layui/__pycache__/Core.cpython-37.pyc
Dominate_Layui/static/__init__.py
Dominate_Layui/static/__pycache__/__init__.cpython-36.pyc
Dominate_Layui/static/__pycache__/__init__.cpython-37.pyc
Dominate_Layui/static/layui/init.js
Dominate_Layui/static/layui/layui.all.js
Dominate_Layui/static/layui/layui.js
Dominate_Layui/static/layui/css/layui.css
Dominate_Layui/static/layui/css/layui.mobile.css
Dominate_Layui/static/layui/css/modules/code.css
Dominate_Layui/static/layui/css/modules/laydate/default/laydate.css
Dominate_Layui/static/layui/css/modules/layer/default/icon-ext.png
Dominate_Layui/static/layui/css/modules/layer/default/icon.png
Dominate_Layui/static/layui/css/modules/layer/default/layer.css
Dominate_Layui/static/layui/css/modules/layer/default/loading-0.gif
Dominate_Layui/static/layui/css/modules/layer/default/loading-1.gif
Dominate_Layui/static/layui/css/modules/layer/default/loading-2.gif
Dominate_Layui/static/layui/font/iconfont.eot
Dominate_Layui/static/layui/font/iconfont.svg
Dominate_Layui/static/layui/font/iconfont.ttf
Dominate_Layui/static/layui/font/iconfont.woff
Dominate_Layui/static/layui/font/iconfont.woff2
Dominate_Layui/static/layui/images/face/0.gif
Dominate_Layui/static/layui/images/face/1.gif
Dominate_Layui/static/layui/images/face/10.gif
Dominate_Layui/static/layui/images/face/11.gif
Dominate_Layui/static/layui/images/face/12.gif
Dominate_Layui/static/layui/images/face/13.gif
Dominate_Layui/static/layui/images/face/14.gif
Dominate_Layui/static/layui/images/face/15.gif
Dominate_Layui/static/layui/images/face/16.gif
Dominate_Layui/static/layui/images/face/17.gif
Dominate_Layui/static/layui/images/face/18.gif
Dominate_Layui/static/layui/images/face/19.gif
Dominate_Layui/static/layui/images/face/2.gif
Dominate_Layui/static/layui/images/face/20.gif
Dominate_Layui/static/layui/images/face/21.gif
Dominate_Layui/static/layui/images/face/22.gif
Dominate_Layui-2020.6.25.post1.dist-info/LICENSE
Dominate_Layui-2020.6.25.post1.dist-info/METADATA
Dominate_Layui-2020.6.25.post1.dist-info/WHEEL
Dominate_Layui-2020.6.25.post1.dist-info/top_level.txt
Dominate_Layui-2020.6.25.post1.dist-info/RECORD
