Metadata-Version: 2.1
Name: Dominate-Layui
Version: 2020.6.25.post1
Summary: A packages for Dominate.Make your website by Layui.
Home-page: https://github.com/BugMaker-project/Dominate_Layui
Author: BM-Business-Dev-Liu
Author-email: Liubaolin20070125@outlook.com
License: UNKNOWN
Platform: UNKNOWN
Classifier: Programming Language :: Python :: 3
Classifier: License :: OSI Approved :: GNU General Public License v3 (GPLv3)
Classifier: Operating System :: Microsoft 
Requires-Python: >=3
